antelope_core/__init__.py
antelope_core/autorange.py
antelope_core/catalog_query.py
antelope_core/characterizations.py
antelope_core/contexts.py
antelope_core/exchanges.py
antelope_core/file_accessor.py
antelope_core/fragment_flows.py
antelope_core/from_json.py
antelope_core/lc_resource.py
antelope_core/lcia_results.py
antelope_core/archives/__init__.py
antelope_core/archives/archive_index.py
antelope_core/archives/basic_archive.py
antelope_core/archives/entity_store.py
antelope_core/archives/lc_archive.py
antelope_core/archives/quantity_manager.py
antelope_core/archives/term_manager.py
antelope_core/archives/data/elcd_reference_quantities.json
antelope_core/archives/tests/__init__.py
antelope_core/archives/tests/test_base.py
antelope_core/archives/tests/test_basic_archive.py
antelope_core/archives/tests/test_entity_store.py
antelope_core/archives/tests/test_json.json
antelope_core/archives/tests/test_qdb.py
antelope_core/archives/tests/test_quantity_manager.py
antelope_core/archives/tests/test_quantity_relation.py
antelope_core/archives/tests/test_term_manager.py
antelope_core/catalog/__init__.py
antelope_core/catalog/catalog.py
antelope_core/catalog/catalog_root.py
antelope_core/catalog/configurator.py
antelope_core/catalog/lc_catalog.py
antelope_core/catalog/lc_resolver.py
antelope_core/catalog/tests/USLCI_Processes_ecospold9.zip
antelope_core/catalog/tests/__init__.py
antelope_core/catalog/tests/test_catalogs.py
antelope_core/catalog/tests/test_process_ref.py
antelope_core/catalog/tests/test_quantity_refs.py
antelope_core/data_sources/__init__.py
antelope_core/data_sources/data_source.py
antelope_core/data_sources/ecoinvent.py
antelope_core/data_sources/ecoinvent_lcia.py
antelope_core/data_sources/gwp_ipcc_2007.py
antelope_core/data_sources/local.py
antelope_core/data_sources/traci.py
antelope_core/data_sources/tests/__init__.py
antelope_core/data_sources/tests/test_aa_local.py
antelope_core/data_sources/tests/test_ecoinvent.py
antelope_core-0.3.7.dist-info/licenses/LICENSE
antelope_core-0.3.7.dist-info/METADATA
antelope_core-0.3.7.dist-info/WHEEL
antelope_core-0.3.7.dist-info/top_level.txt
antelope_core-0.3.7.dist-info/RECORD
