Metadata-Version: 2.4
Name: antelope_core
Version: 0.3.7
Home-page: https://github.com/AntelopeLCA/core
Author: Brandon Kuczenski
Author-email: bkuczenski@ucsb.edu
License: BSD 3-Clause
Classifier: Development Status :: 4 - Beta
Classifier: Intended Audience :: Science/Research
Classifier: License :: OSI Approved :: BSD License
Classifier: Natural Language :: English
Classifier: Operating System :: OS Independent
Classifier: Programming Language :: Python :: 3
Classifier: Topic :: Scientific/Engineering
Requires-Python: >=3.6
License-File: LICENSE
Requires-Dist: synonym_dict>=0.2.4
Requires-Dist: antelope_interface>=0.3.3
Requires-Dist: xlstools>=0.1.6
Requires-Dist: python-magic>=0.4.18
Requires-Dist: requests>=2.25
Requires-Dist: pydantic>=2.5.0
Provides-Extra: xml
Requires-Dist: lxml>=1.2.0; extra == "xml"
Provides-Extra: write-to-excel
Requires-Dist: xlsxwriter>=1.3.7; extra == "write-to-excel"
Dynamic: author
Dynamic: author-email
Dynamic: classifier
Dynamic: description
Dynamic: description-content-type
Dynamic: home-page
Dynamic: license
Dynamic: license-file
Dynamic: provides-extra
Dynamic: requires-dist
Dynamic: requires-python
